{
    "Material": "Hf4Cr",
    "steinhart_vector": [
        [
            0.0058694307413547945,
            5.54746519959011e-19,
            8.551017685294313e-19,
            0.004374815375632103,
            0.0029885678509510138,
            2.1139177774159708e-18,
            0.00368916824792601,
            0.0035918115422690342,
            0.0012487893553047695,
            0.003039955997656691,
            0.003816031924139947
        ],
        "Hf4Cr"
    ],
    "steinhart_parameter_sum": 0.028618571035234366,
    "band_gap": 0.0,
    "oxidation_state": "Oxidation state not available",
    "possible_species": [],
    "density": 11.312187555322138,
    "quadrupole moment": "Could not compute",
    "quadrupole moment normalized": "Could not compute"
}